<?xml version="1.0" encoding="UTF-8"?>
<objects serializationModel="Studio.02.02.00">
	<object class="AudioFile" id="{34cc715a-10fc-4d4d-98b3-4da2a8d9a95e}">
		<property name="assetPath">
			<value>slash3.mp3</value>
		</property>
		<property name="frequencyInKHz">
			<value>44.0999985</value>
		</property>
		<property name="channelCount">
			<value>2</value>
		</property>
		<property name="length">
			<value>0.67918367346938779</value>
		</property>
		<relationship name="masterAssetFolder">
			<destination>{343686ea-61e4-495f-af4b-8943f6b4c417}</destination>
		</relationship>
	</object>
</objects>
